dakan_eda/__init__.py
dakan_eda/eda.py
dakan_eda-0.0.12.dist-info/LICENSE
dakan_eda-0.0.12.dist-info/WHEEL
dakan_eda-0.0.12.dist-info/METADATA
dakan_eda-0.0.12.dist-info/RECORD
